depy.py
setup.py
depy.egg-info/PKG-INFO
depy.egg-info/SOURCES.txt
depy.egg-info/dependency_links.txt
depy.egg-info/entry_points.txt
depy.egg-info/requires.txt
depy.egg-info/top_level.txt