Metadata-Version: 1.1
Name: depy
Version: 0.0.2
Summary: Python non-importing module dependency analysis tool. Aims to be simple.
